slandroid/__init__.py
slandroid/slandroid_compiler.py
slandroid/tool.py
slandroid-0.3.7.dist-info/LICENSE
slandroid-0.3.7.dist-info/METADATA
slandroid-0.3.7.dist-info/WHEEL
slandroid-0.3.7.dist-info/entry_points.txt
slandroid-0.3.7.dist-info/top_level.txt
slandroid-0.3.7.dist-info/RECORD
