Metadata-Version: 2.2
Name: slandroid
Version: 0.3.7
Summary: A universal script runner for multiple programming languages. Automatically detects and runs scripts in Python, JavaScript, Bash, Ruby, Java, Go, PHP, Perl, C, C++, Rust, and more.
Home-page: https://github.com/ishanoshada/sl-android
Author: Ishan Oshada (SL ANDROID TEAM)
Author-email: ishan.kodithuwakku.offical@gmail.com
License: MIT
Project-URL: Source, https://github.com/ishanoshada/sl-android
Project-URL: Bug Reports, https://github.com/ishanoshada/sl-android/issues
Project-URL: Documentation, https://github.com/ishanoshada/sl-android#readme
Keywords: script runner,multi-language,python,javascript,bash,ruby,java,go,php,perl,c,c++,rust,automation,developer tools
Classifier: Development Status :: 4 - Beta
Classifier: Intended Audience :: Developers
Classifier: License :: OSI Approved :: MIT License
Classifier: Programming Language :: Python :: 3
Classifier: Programming Language :: Python :: 3.6
Classifier: Programming Language :: Python :: 3.7
Classifier: Programming Language :: Python :: 3.8
Classifier: Programming Language :: Python :: 3.9
Classifier: Programming Language :: Python :: 3.10
Classifier: Operating System :: OS Independent
Classifier: Topic :: Software Development :: Libraries :: Python Modules
Classifier: Topic :: Utilities
Classifier: Environment :: Console
License-File: LICENSE
Requires-Dist: requests
Requires-Dist: packaging
Dynamic: author
Dynamic: author-email
Dynamic: classifier
Dynamic: description
Dynamic: description-content-type
Dynamic: home-page
Dynamic: keywords
Dynamic: license
Dynamic: project-url
Dynamic: requires-dist
Dynamic: summary
